passlib-stubs/METADATA.toml
passlib-stubs/__init__.pyi
passlib-stubs/apache.pyi
passlib-stubs/apps.pyi
passlib-stubs/context.pyi
passlib-stubs/exc.pyi
passlib-stubs/hash.pyi
passlib-stubs/hosts.pyi
passlib-stubs/ifc.pyi
passlib-stubs/pwd.pyi
passlib-stubs/py.typed
passlib-stubs/registry.pyi
passlib-stubs/totp.pyi
passlib-stubs/win32.pyi
passlib-stubs/crypto/__init__.pyi
passlib-stubs/crypto/_md4.pyi
passlib-stubs/crypto/des.pyi
passlib-stubs/crypto/digest.pyi
passlib-stubs/crypto/_blowfish/__init__.pyi
passlib-stubs/crypto/_blowfish/_gen_files.pyi
passlib-stubs/crypto/_blowfish/base.pyi
passlib-stubs/crypto/_blowfish/unrolled.pyi
passlib-stubs/crypto/scrypt/__init__.pyi
passlib-stubs/crypto/scrypt/_builtin.pyi
passlib-stubs/crypto/scrypt/_gen_files.pyi
passlib-stubs/crypto/scrypt/_salsa.pyi
passlib-stubs/ext/__init__.pyi
passlib-stubs/ext/django/__init__.pyi
passlib-stubs/ext/django/models.pyi
passlib-stubs/ext/django/utils.pyi
passlib-stubs/handlers/__init__.pyi
passlib-stubs/handlers/argon2.pyi
passlib-stubs/handlers/bcrypt.pyi
passlib-stubs/handlers/cisco.pyi
passlib-stubs/handlers/des_crypt.pyi
passlib-stubs/handlers/digests.pyi
passlib-stubs/handlers/django.pyi
passlib-stubs/handlers/fshp.pyi
passlib-stubs/handlers/ldap_digests.pyi
passlib-stubs/handlers/md5_crypt.pyi
passlib-stubs/handlers/misc.pyi
passlib-stubs/handlers/mssql.pyi
passlib-stubs/handlers/mysql.pyi
passlib-stubs/handlers/oracle.pyi
passlib-stubs/handlers/pbkdf2.pyi
passlib-stubs/handlers/phpass.pyi
passlib-stubs/handlers/postgres.pyi
passlib-stubs/handlers/roundup.pyi
passlib-stubs/handlers/scram.pyi
passlib-stubs/handlers/scrypt.pyi
passlib-stubs/handlers/sha1_crypt.pyi
passlib-stubs/handlers/sha2_crypt.pyi
passlib-stubs/handlers/sun_md5_crypt.pyi
passlib-stubs/handlers/windows.pyi
passlib-stubs/utils/__init__.pyi
passlib-stubs/utils/binary.pyi
passlib-stubs/utils/decor.pyi
passlib-stubs/utils/des.pyi
passlib-stubs/utils/handlers.pyi
passlib-stubs/utils/md4.pyi
passlib-stubs/utils/pbkdf2.pyi
types_passlib-1.7.7.20250601.dist-info/licenses/LICENSE
types_passlib-1.7.7.20250601.dist-info/METADATA
types_passlib-1.7.7.20250601.dist-info/WHEEL
types_passlib-1.7.7.20250601.dist-info/top_level.txt
types_passlib-1.7.7.20250601.dist-info/RECORD
